{
  "hash": "bb0893d9",
  "configHash": "8afe0f30",
  "lockfileHash": "10c2bb45",
  "browserHash": "f70577a3",
  "optimized": {
    "react-dom/client": {
      "src": "../../node_modules/react-dom/client.js",
      "file": "react-dom_client.js",
      "fileHash": "2de9e5b6",
      "needsInterop": true
    },
    "react": {
      "src": "../../node_modules/react/index.js",
      "file": "react.js",
      "fileHash": "a5f16088",
      "needsInterop": true
    },
    "react-router-dom": {
      "src": "../../node_modules/react-router-dom/dist/index.js",
      "file": "react-router-dom.js",
      "fileHash": "e8d10c5d",
      "needsInterop": false
    },
    "recoil": {
      "src": "../../node_modules/recoil/es/index.js",
      "file": "recoil.js",
      "fileHash": "f38a7dc6",
      "needsInterop": false
    },
    "socket.io-client": {
      "src": "../../node_modules/socket.io-client/build/esm/index.js",
      "file": "socket__io-client.js",
      "fileHash": "ca85101e",
      "needsInterop": false
    }
  },
  "chunks": {
    "chunk-PXJLUKTU": {
      "file": "chunk-PXJLUKTU.js"
    },
    "chunk-FQO5W7GE": {
      "file": "chunk-FQO5W7GE.js"
    },
    "chunk-ZS7NZCD4": {
      "file": "chunk-ZS7NZCD4.js"
    }
  }
}